pytest_click/__init__.py
pytest_click/fixtures.py
pytest_click-1.1.0.dist-info/LICENSE
pytest_click-1.1.0.dist-info/METADATA
pytest_click-1.1.0.dist-info/WHEEL
pytest_click-1.1.0.dist-info/entry_points.txt
pytest_click-1.1.0.dist-info/top_level.txt
pytest_click-1.1.0.dist-info/RECORD
