Metadata-Version: 2.1
Name: pytest-click
Version: 1.1.0
Summary: Pytest plugin for Click
Home-page: https://github.com/Stranger6667/pytest-click
Author: Dmitry Dygalo
Author-email: dadygalo@gmail.com
Maintainer: Dmitry Dygalo
Maintainer-email: dadygalo@gmail.com
License: MIT
Platform: UNKNOWN
Classifier: Development Status :: 5 - Production/Stable
Classifier: Environment :: Console
Classifier: Intended Audience :: Developers
Classifier: Operating System :: OS Independent
Classifier: License :: OSI Approved :: MIT License
Classifier: Programming Language :: Python
Classifier: Programming Language :: Python :: 3.7
Classifier: Programming Language :: Python :: 3.8
Classifier: Programming Language :: Python :: 3.9
Classifier: Programming Language :: Python :: 3.10
Classifier: Programming Language :: Python :: Implementation :: CPython
Classifier: Programming Language :: Python :: Implementation :: PyPy
Classifier: Topic :: Software Development :: Testing
License-File: LICENSE
